koboapi/__init__.py
koboapi/exceptions.py
koboapi/http_client.py
koboapi/models.py
koboapi/parsers.py
koboapi/wrapper.py
koboapi-0.1.0.dist-info/licenses/LICENSE
koboapi-0.1.0.dist-info/METADATA
koboapi-0.1.0.dist-info/WHEEL
koboapi-0.1.0.dist-info/top_level.txt
koboapi-0.1.0.dist-info/RECORD
