Metadata-Version: 2.4
Name: koboapi
Version: 0.1.0
Summary: A Python package for interacting with KoBo Toolbox API
Author-email: Your Name <your.email@example.com>
License: MIT
Project-URL: Homepage, https://github.com/morabdiego/koboapi
Project-URL: Bug Reports, https://github.com/morabdiego/koboapi/issues
Project-URL: Source, https://github.com/morabdiego/koboapi
Classifier: Development Status :: 3 - Alpha
Classifier: Intended Audience :: Developers
Classifier: License :: OSI Approved :: MIT License
Classifier: Operating System :: OS Independent
Classifier: Programming Language :: Python :: 3
Classifier: Programming Language :: Python :: 3.8
Classifier: Programming Language :: Python :: 3.9
Classifier: Programming Language :: Python :: 3.10
Classifier: Programming Language :: Python :: 3.11
Classifier: Programming Language :: Python :: 3.12
Requires-Python: >=3.8
License-File: LICENSE
Requires-Dist: requests
Provides-Extra: dev
Requires-Dist: pytest; extra == "dev"
Dynamic: license-file
